{"articles": [{"title": "على خطى \"ديب سيك\".. نموذج صيني ينافس عمالقة التقنية", "description": "أطلقت شركة «مون شوت إيه آي» الصينية نموذج الذكاء الاصطناعي الجديد «كيمي K3»، في خطوة...", "url": "https://www.okaz.com.sa/variety/na/2258349", "urlToImage": "https://www.okaz.com.sa/okaz/uploads/images/2026/07/24/2741349.webp", "publishedAt": "2026-07-23T21:16:00Z", "source": {"name": "عكاظ"}}, {"title": "الكاميرا الخلفية لا تكفي!", "description": "تتعرّض سيارات الطوارئ ومن بداخلها للخطر من بعض المتعجلين، في الوقت الذي يجب فيه إفساح...", "url": "https://www.okaz.com.sa/local/na/2258357", "urlToImage": "https://www.okaz.com.sa/okaz/uploads/images/2026/07/24/2741525.webp", "publishedAt": "2026-07-23T21:16:00Z", "source": {"name": "عكاظ"}}, {"title": "\"الذكاء الاصطناعي الخفي\" يورطك وشركتك.. فكيف تتعامل معه؟", "description": "تستخدم نماذج الذكاء الاصطناعي البيانات التي يشاركها المستخدمون مباشرة مع النموذج في محادثاتهم دون التفرقة بين البيانات السرية للشركات والبيانات العامة للمستخدمين، وهو ما يضع الشركة في خطر", "url": "https://www.aljazeera.net/tech/2026/7/23/%D8%A7%D9%84%D8%B0%D9%83%D8%A7%D8%A1-%D8%A7%D9%84%D8%A7%D8%B5%D8%B7%D9%86%D8%A7%D8%B9%D9%8A-%D8%A7%D9%84%D8%AE%D9%81%D9%8A-%D9%8A%D9%88%D8%B1%D8%B7%D9%83-%D9%88%D8%B4%D8%B1%D9%83%D8%AA%D9%83", "urlToImage": "https://www.aljazeera.net/wp-content/uploads/2026/07/Gemini_Ge-1784812690.png?resize=1920%2C1440", "publishedAt": "2026-07-23T19:07:35Z", "source": {"name": "الجزيرة نت"}}, {"title": "استثمار أخطر من البيتكوين", "description": "لطالما اعتبر المستثمرون العملات المشفرة -وخاصة \"بيتكوين\"- الأكثر تقلبًا بين الأصول المالية، حتى أصبحت مرادفًا للمخاطر، لكن هذا العام، برز منافس غير مت", "url": "https://www.argaam.com/ar/article/articledetail/id/1921986", "urlToImage": "https://argaamplus.s3.amazonaws.com/177920de-738b-4916-996f-488344f0b174.png", "publishedAt": "2026-07-23T18:12:05Z", "source": {"name": "Argaam"}}, {"title": "HONOR تعلن بدء البيع الرسمي لهاتف HONOR X7e Plus 5G", "description": "أعلنت HONOR، العلامة الرائدة عالمياً في الأجهزة المدعومة بالذكاء الاصطناعي، عن بدء البيع الرسمي لهاتف HONOR X7e Plus 5G ، ليقدم للمستخدمين تجربة متكاملة", "url": "https://shafaq-e.sa/475522.html", "urlToImage": "https://shafaq-e.sa/wp-content/uploads/2026/07/WhatsApp-Image-2026-07-23-at-12.35.07-PM.jpeg", "publishedAt": "2026-07-23T17:43:34Z", "source": {"name": "صحيفة شفق الإلكترونية"}}, {"title": "بعد السيارات الاقتصادية.. الصين تستهدف عرش السيارات الفاخرة في أوروبا", "description": "تسعى شركات التكنولوجيا الصينية إلى اقتحام سوق السيارات الفاخرة في أوروبا عبر التركيز على البرمجيات والقيادة الذكية، في تحد مباشر للعلامات الألمانية التي هيمنت على هذا القطاع لعقود.", "url": "https://www.aljazeera.net/ebusiness/2026/7/23/%D8%A8%D8%B9%D8%AF-%D8%A7%D9%84%D8%B3%D9%8A%D8%A7%D8%B1%D8%A7%D8%AA-%D8%A7%D9%84%D8%A7%D9%82%D8%AA%D8%B5%D8%A7%D8%AF%D9%8A%D8%A9-%D8%A7%D9%84%D8%B5%D9%8A%D9%86-%D8%AA%D8%B3%D8%AA%D9%87%D8%AF%D9%81", "urlToImage": "https://www.aljazeera.net/wp-content/uploads/2026/07/RC2N7KAEEG49-1784821229.jpg?resize=1920%2C1440", "publishedAt": "2026-07-23T16:03:52Z", "source": {"name": "الجزيرة نت"}}, {"title": "الذكاء الاصطناعي يبحث عن مراهقي الصين.. الشركات تصطاد المواهب من سن 13", "description": "بدأت الشركات الصينية تتجه إلى طلاب المدارس الثانوية بحثا عن المهارات الفذة في قطاع الذكاء الاصطناعي وسط ارتفاع الطلب على هذه المهارات ونقص العاملين بها.", "url": "https://www.aljazeera.net/tech/2026/7/23/%D8%A7%D9%84%D8%B0%D9%83%D8%A7%D8%A1-%D8%A7%D9%84%D8%A7%D8%B5%D8%B7%D9%86%D8%A7%D8%B9%D9%8A-%D9%8A%D8%A8%D8%AD%D8%AB-%D8%B9%D9%86-%D9%85%D8%B1%D8%A7%D9%87%D9%82%D9%8A-%D8%A7%D9%84%D8%B5%D9%8A%D9%86", "urlToImage": "https://www.aljazeera.net/wp-content/uploads/2026/07/2kids-1784810279.jpeg?resize=1920%2C1440", "publishedAt": "2026-07-23T14:48:20Z", "source": {"name": "الجزيرة نت"}}, {"title": "1.4 مليون شخص يواجهون \"انعدام الأمن الغذائي\" في غزة", "description": "حذر تصنيف الأمم المتحدة المرحلي للأمن الغذائي من أن أكثر من 1.4 مليون شخص في غزة ما زالوا...", "url": "https://www.okaz.com.sa/variety/na/2258307", "urlToImage": "https://www.okaz.com.sa/okaz/uploads/images/2026/07/23/2741343.webp", "publishedAt": "2026-07-23T14:36:00Z", "source": {"name": "عكاظ"}}, {"title": "أوروبا تصفع \"غوغل\" بغرامة ضخمة.. وتخاطر بصدام مع ترامب", "description": "فرض الاتحاد الأوروبي غرامة قيمتها 890 مليون يورو (1.015 مليار دولار) على شركة غوغل بسبب انتهاكها القواعد الرقمية الأوروبية.", "url": "https://www.skynewsarabia.com/technology/1882460-%D8%A3%D9%88%D8%B1%D9%88%D8%A8%D8%A7-%D8%AA%D8%B5%D9%81%D8%B9-%D8%BA%D9%88%D8%BA%D9%84-%D8%A8%D8%BA%D8%B1%D8%A7%D9%85%D8%A9-%D8%B6%D8%AE%D9%85%D8%A9-%D9%88%D8%AA%D8%AE%D8%A7%D8%B7%D8%B1-%D8%A8%D8%B5%D8%AF%D8%A7%D9%85-%D8%AA%D8%B1%D8%A7%D9%85%D8%A8", "urlToImage": "https://www.skynewsarabia.com/images/v2/2026/07/02/1878746/1200/630/1-1878746.JPG", "publishedAt": "2026-07-23T13:45:58Z", "source": {"name": "سكاي نيوز عربية"}}, {"title": "من الرخص التجارية إلى الدعم السكني.. 70 خدمة جديدة عبر توكلنا", "description": "أتاحت وزارة البلديات والإسكان أكثر من 70 خدمة رقمية عبر التطبيق الوطني الشامل «توكلنا»، بما يمكّن الأفراد والمنشآت والمستثمرين من إنجاز مجموعة واسعة من الإجراءات البلدية والإسكانية والعقارية عبر قناة رقمية موحدة وموثوقة. وتأتي الخطوة ضمن جهود الوزارة لتوسيع نطاق خدماتها الإلكترونية، وتسهيل وصول المستفيدين إليها، وتقليل الحاجة إلى مراجعة الجهات المختصة حضوريًا، مع إتاحة [...] تم نشر هذه المقالة من الرخص التجارية إلى الدعم السكني.. 70 خدمة جديدة عبر توكلنا للمرة الأولي علي صحيفة الوئام .", "url": "https://www.alweeam.com.sa/1286910/2026/%D9%85%D9%86-%D8%A7%D9%84%D8%B1%D8%AE%D8%B5-%D8%A7%D9%84%D8%AA%D8%AC%D8%A7%D8%B1%D9%8A%D8%A9-%D8%A5%D9%84%D9%89-%D8%A7%D9%84%D8%AF%D8%B9%D9%85-%D8%A7%D9%84%D8%B3%D9%83%D9%86%D9%8A-70-%D8%AE%D8%AF/", "urlToImage": "https://www.alweeam.com.sa/wp-content/uploads/2026/07/%D8%AA%D9%88%D9%83%D9%84%D9%86%D8%A7.jpg", "publishedAt": "2026-07-24 03:05:43", "source": {"name": "alweeam"}}, {"title": "الصين تطلق قمرًا اصطناعيًا إلى الفضاء لنقل البيانات", "description": "أطلقت الصين بنجاح، الخميس، قمرًا اصطناعيًا جديدًا لنقل البيانات، إلى مداره، من مركز شيتشانغ لإطلاق الأقمار الاصطناعية في مقاطعة سيتشوان جنوب غرب الصين.وأفادت وكالة أنباء الصين الجديدة (شينخوا) أن القمر الاصطناعي \"تيانليان II-06\" أُطلق في تمام الساعة الثامنة مساءً (بتوقيت بكين) على متن صاروخ حامل من طراز \"لونغ مارش-3 بي\"، ودخل مداره المخطط له. خدمات...", "url": "https://gulf365.net/technology/13220903/%D8%A7%D9%84%D8%B5%D9%8A%D9%86-%D8%AA%D8%B7%D9%84%D9%82-%D9%82%D9%85%D8%B1%D9%8B%D8%A7-%D8%A7%D8%B5%D8%B7%D9%86%D8%A7%D8%B9%D9%8A%D9%8B%D8%A7-%D8%A5%D9%84%D9%89-%D8%A7%D9%84%D9%81%D8%B6%D8%A7%D8%A1-%D9%84%D9%86%D9%82%D9%84-%D8%A7%D9%84%D8%A8%D9%8A%D8%A7%D9%86%D8%A7%D8%AA.html", "urlToImage": "https://gulf365.net/content/uploads/2026/07/24/4ccbd70645.jpg", "publishedAt": "2026-07-24 00:28:12", "source": {"name": "gulf365"}}, {"title": "\"الطرق\": مساران حيويان يربطان الرياض بالباحة عبر شبكة متطورة", "description": "<p>شهدت المملكة تطورًا ملحوظًا في شبكة طرقها التي تمتد لأكثر من 73 ألف كيلومتر، ما مكّنها من تصدر المرتبة الأولى عالميا في مؤشر ترابط شبكة الطرق، وذلك وفق تقارير منتدى التنافسية العالمي، وهو ما يُسهم في تعزيز الربط بين المدن والمحافظات، وخدمة مستخدمي الطرق، وتسهيل حركة تنقلهم.</p><p>وأوضحت \"<a href=\"https://www.alyaum.com/articles/6673283/%D8%A7%D9%84%D8%A3%D8%AE%D8%A8%D8%A7%D8%B1/%D8%A7%D9%84%D9%85%D9%85%D9%84%D9%83%D8%A9-%D8%A7%D9%84%D9%8A%D9%88%D9%85/%D9%87%D9%8A%D8%A6%D8%A9-%D8%A7%D9%84%D8%B7%D8%B1%D9%82-%D9%83%D9%88%D8%AF-%D8%A7%D9%84%D8%B7%D8%B1%D9%82-%D9%8A%D8%B6%D9%85%D9%86-%D8%A7%D9%86%D8%B3%D9%8A%D8%A7%D8%A8%D9%8A%D8%A9-%D8%A7%D9%84%D8%AD%D8%B1%D9%83%D8%A9-%D9%81%D9%8A-%D8%A7%D9%84%D8%A3%D8%AD%D8%AF%D8%A7%D8%AB-%D8%A7%D9%84%D9%83%D8%A8%D8%B1%D9%89\" target=\"_blank\">هيئة الطرق</a>\" أن قطاع الطرق يمثل ركيزة أساسية وممكنًا حيويًا للعديد من القطاعات الأخرى، وفي مقدمتها قطاع السياحة، لافتة إلى أن منطقة الباحة تتمتع بشبكة طرق متطورة تمتد لأكثر من 1777 كيلومترًا، وتُشكل شريانًا حيويًا يعزز مكانة المنطقة بوصفها واحدة من أبرز الوجهات السياحية الجبلية في المملكة.<br />وتأتي هذه الشبكة ضمن جهود الهيئة لتسهيل وصول الزوار والسياح إلى الغابات الكثيفة والمعالم الطبيعية والقرى التراثية التي تزخر بها المنطقة، بما يتيح لهم استكشاف جمالها الطبيعي وتاريخها العريق.</p><h2>مساران رئيسيان متنوعان</h2><p>وبيّنت الهيئة أن المسافرين برًا من مدينة الرياض إلى منطقة الباحة يتاح لهم مساران رئيسيان متنوعان، يختلفان في طول المسافة ومدة الرحلة والمحطات التي يمران بها، وذلك في إطار تسهيل تنقلات مستخدمي الطرق وتوفير خيارات متعددة للوصول إلى الباحة.</p><p>ويتمثل المسار الأول، وهو الأسرع، في الانطلاق من الرياض مرورًا ببيشة وصولًا إلى الباحة، ويبلغ طوله نحو 877 كيلومترًا، وتستغرق الرحلة عبره نحو 9 ساعات.<br />أما المسار الثاني، فيمر بمحافظة الطائف، ويبلغ طوله نحو 1010 كيلومترات، وتُقطع الرحلة عبره في نحو 10 ساعات.</p><h2>تنوع جغرافي وبيئي فريد</h2><p>وتتميز منطقة الباحة الواقعة في جنوب غرب المملكة، بتنوع جغرافي وبيئي فريد، إذ تجمع بين مرتفعات جبال السروات الشاهقة وسهول تهامة المنخفضة.<br />وتضم المنطقة تضاريس متباينة تشمل القمم الجبلية التي تكسوها الخضرة، والوديان العميقة، بالإضافة إلى العديد من الغابات الطبيعية تجعل منها مقصدًا سياحيًا رئيسيًا.</p><p> </p>", "url": "https://www.alyaum.com/articles/6674544/%D8%A7%D9%84%D8%A3%D8%AE%D8%A8%D8%A7%D8%B1/%D8%A7%D9%84%D9%85%D9%85%D9%84%D9%83%D8%A9-%D8%A7%D9%84%D9%8A%D9%88%D9%85/%D8%A7%D9%84%D8%B7%D8%B1%D9%82-%D9%85%D8%B3%D8%A7%D8%B1%D8%A7%D9%86-%D8%AD%D9%8A%D9%88%D9%8A%D8%A7%D9%86-%D9%8A%D8%B1%D8%A8%D8%B7%D8%A7%D9%86-%D8%A7%D9%84%D8%B1%D9%8A%D8%A7%D8%B6-%D8%A8%D8%A7%D9%84%D8%A8%D8%A7%D8%AD%D8%A9-%D8%B9%D8%A8%D8%B1-%D8%B4%D8%A8%D9%83%D8%A9-%D9%85%D8%AA%D8%B7%D9%88%D8%B1%D8%A9", "urlToImage": "https://www.alyaum.com/uploads/images/2026/07/24/3058046.jpg", "publishedAt": "2026-07-23 21:35:00", "source": {"name": "alyaum"}}, {"title": "على خطى «ديب سيك».. نموذج صيني ينافس عمالقة التقنية", "description": "أطلقت شركة «مون شوت إيه آي» الصينية نموذج الذكاء الاصطناعي الجديد «كيمي K3»، في خطوة أثارت اهتماماً واسعاً داخل قطاع التقنية، وأعادت إلى الواجهة صعود النماذج الصينية المفتوحة بعد تجربة «ديب سيك».ويضم النموذج 2.8 تريليون معلمة، ما يجعله أكبر نموذج مفتوح الأوزان حتى الآن، مع قدرات متقدّمة في البرمجة وتنفيذ المهام المعقّدة، ليضعه في منافسة مباشرة مع نماذج طوّرتها شركتا «أوبن إيه آي» و«أنثروبيك» الأمريكيتان.واعتمدت الشركة في تطوير النموذج على بنية تساعد في خفض قوة المعالجة المطلوبة، وسط القيود المفروضة على وصول الصين إلى شرائح الذكاء الاصطناعي المتقدّمة. ويتطلب تشغيله محلياً ذاكرة كبيرة وبنية تقنية متطورة، ما قد يحد من انتشاره بين بعض الشركات والمستخدمين.ودفع الإقبال الواسع على «كيمي K3» الشركة إلى تعليق الاشتراكات الجديدة مؤقتاً، في مؤشر يعكس الاهتمام المتزايد بالنموذج، الذي يعزّز حضور الصين في سباق الذكاء الاصطناعي العالمي، ويرفع مستوى المنافسة مع الشركات الأمريكية.", "url": "https://www.okaz.com.sa/variety/na/2258349", "urlToImage": "https://www.okaz.com.sa/okaz/uploads/images/2026/07/24/2741349.webp", "publishedAt": "2026-07-23 21:16:22", "source": {"name": "okaz"}}, {"title": "اتفاقية تاريخية", "description": "في مرحلة دولية تتسارع فيها التحولات الجيوسياسية، يتقدم أمن الطاقة والتقنيات المتقدمة إلى صدارة أولويات الدول، مع حضور متزايد لملفات الاستدامة والابتكار والتعاون العلمي ضمن أجندة العلاقات الدولية. وتشهد أسواق الطاقة إعادة تشكيل واسعة، تتزامن مع توسع الاستثمار في مصادر الطاقة منخفضة الانبعاثات، وتنامي الاهتمام العالمي بالطاقة النووية السلمية بوصفها أحد الخيارات المستقبلية لدعم أمن الإمدادات وتحقيق مستهدفات التنمية. وفي هذا السياق، وقعت المملكة العربية السعودية والولايات المتحدة الأميركية اتفاقية تعاون في مجال الاستخدامات السلمية للطاقة النووية، ضمن إطار الشراكة الاستراتيجية التي تجمع البلدين، وتعكس الاتفاقية مرحلة جديدة من التعاون في مجالات الطاقة والتقنيات المتقدمة، مع الالتزام الكامل بأعلى معايير الأمن والأمان النوويين وعدم الانتشار. وتحمل الاتفاقية أبعادًا تتجاوز الجانب الفني، مع حضور واضح لبناء شراكة طويلة المدى في مجالات البحث والتطوير، ونقل المعرفة، وتبادل الخبرات، وإعداد الكفاءات الوطنية، إلى جانب فتح آفاق أوسع أمام الاستثمار في التقنيات النووية السلمية. ويأتي ذلك ضمن توجه المملكة نحو تنويع مزيج الطاقة، وتعزيز كفاءة منظومة الطاقة الوطنية، ودعم مسارات الابتكار العلمي. وحظيت الاتفاقية باهتمام واسع في وسائل الإعلام الدولية، التي تناولتها من زوايا متعددة. حيث إنها تمثل محطة بارزة في مسار العلاقات السعودية الأميركية، مع تركيز على الفرص الاستثمارية، ومستقبل الصناعة النووية المدنية، وحضور الشركات الأميركية في المشروعات المستقبلية. ويعكس هذا الاهتمام المكانة التي أصبحت تحتلها المملكة في المشهد العالمي للطاقة، والدور الذي تؤديه في رسم ملامح مستقبلها، عبر مشروعات نوعية تستند إلى التخطيط طويل الأمد، والاستثمار في التقنيات المتقدمة، وبناء شراكات دولية تقوم على المصالح المشتركة، والالتزام بالمعايير الدولية، والرؤية التنموية المستدامة. وتؤكد الاتفاقية اتساع آفاق التعاون السعودي الأمريكي في القطاعات المستقبلية، مع حضور متزايد لمجالات الابتكار والاقتصاد المعرفي ضمن العلاقات الثنائية. كما تمثل خطوة جديدة في مسيرة تطوير قطاع الطاقة، وتعزيز قدراته التقنية، وترسيخ موقع المملكة بوصفها شريكًا رئيساً في المبادرات الدولية المرتبطة بالطاقة والتنمية المستدامة، ومن المتوقع أن تسهم الاتفاقية في تعزيز حضور المملكة داخل المنظمات والمبادرات الدولية المعنية بالطاقة النووية السلمية، بما يوسع مشاركتها في صياغة المعايير الفنية، وبرامج التدريب، والمشروعات البحثية متعددة الأطراف، ويمنحها دورًا أكبر في مستقبل حوكمة الطاقة النووية للأغراض السلمية على المستوى الدولي.", "url": "https://www.alriyadh.com/%3Ehttp:/www.alriyadh.com/2199273", "urlToImage": "", "publishedAt": "2026-07-23 21:08:18", "source": {"name": "alriyadh"}}, {"title": "هل تنسى كلمات المرور؟.. غوغل تختبر «فيديو سيلفي» لاستعادة الحسابات", "description": "تختبر شركة «غوغل» طريقة جديدة لتسجيل الدخول إلى الحسابات تعتمد على تصوير مقطع فيديو قصير للوجه، بهدف توفير خيار احتياطي للمستخدمين الذين يفقدون القدرة على الوصول إلى هواتفهم أو أجهزتهم التي يعتادون استخدامها. دواعي استخدام «فيديو سيلفي» لاستعادة الحسابات تستهدف هذه الميزة بصورة أساسية الحالات التي يستحيل فيها تسجيل الدخول بواسطة الوسائل المتاحة، إذ يمكن [...] تم نشر هذه المقالة هل تنسى كلمات المرور؟.. غوغل تختبر «فيديو سيلفي» لاستعادة الحسابات للمرة الأولي علي صحيفة الوئام .", "url": "https://www.alweeam.com.sa/1286872/2026/%D9%87%D9%84-%D8%AA%D9%86%D8%B3%D9%89-%D9%83%D9%84%D9%85%D8%A7%D8%AA-%D8%A7%D9%84%D9%85%D8%B1%D9%88%D8%B1%D8%9F-%D8%BA%D9%88%D8%BA%D9%84-%D8%AA%D8%AE%D8%AA%D8%A8%D8%B1-%D9%81%D9%8A%D8%AF%D9%8A/", "urlToImage": "https://www.alweeam.com.sa/wp-content/uploads/2026/07/%D9%85%D9%8A%D8%B2%D8%A9-%D9%81%D9%8A%D8%AF%D9%8A%D9%88-%D8%B3%D9%8A%D9%84%D9%81%D9%8A-%D9%84%D8%A7%D8%B3%D8%AA%D8%B9%D8%A7%D8%AF%D8%A9-%D8%A7%D9%84%D8%AD%D8%B3%D8%A7%D8%A8%D8%A7%D8%AA.jpg", "publishedAt": "2026-07-23 20:53:53", "source": {"name": "alweeam"}}, {"title": "ميزة جديدة من غوغل.. كيف تنقل بياناتك بأمان من \"آيفون\" إلى \"أندرويد 17\"؟ - إرم نيوز", "description": "ميزة جديدة من غوغل.. كيف تنقل بياناتك بأمان من \"آيفون\" إلى \"أندرويد 17\"؟ إرم نيوز \"غوغل\" تُسهّل الانتقال من آيفون إلى أندرويد العربية جوجل تسهّل الانتقال من آيفون إلى أندرويد دون تطبيقات عبر أندرويد 17 البوابة التقنية أندرويد 17 يجلب أداة جديدة لنقل البيانات من iPhone إلى هواتف سامسونج القابلة للطي 25h.app تحديث جديد لتطبيق جهات الاتصال من غوغل يسهّل مشاركة رقمك... جريدة الغد", "url": "https://news.google.com/rss/articles/CBMiYkFVX3lxTE5HQlpzVTNuREp2M19BQk5OVjVQV0FpMEtBbEN1eFRkOHpRb3h0LXE2RF9UaXVGaWFnd0doVFZJc2xmVjVnTWFYclE1elFoWDk1NS1iOUtEZnFHbHpraC1kMzVB?oc=5", "urlToImage": "", "publishedAt": "2026-07-23 20:45:43", "source": {"name": "google"}}, {"title": "الذكاء الاصطناعي وكرامة الإنسان", "description": "في لحظة توافقية نادرة بين علماء الاقتصاد ورواد التكنولوجيا، رفع 200 خبير عالمي أصواتهم في تحذير مشترك، مؤكدين أن الذكاء الاصطناعي ليس مجرد أداة تقنية عابرة، بل قوة اقتصادية قد تعيد تشكيل عالمنا بسرعة تفوق كل ما عرفناه في التاريخ الحديث، والمدهش أن من بين هؤلاء الخبراء 15 حائزاً على جائزة نوبل في الاقتصاد، وكبار رواد وادي السليكون، وخاصة مختبري «أنثروبيك»، و»أوبن إيه آي»، بالإضافة إلى شخصيات بارزة مثل جاك كلارك مؤسس أنثروبيك، وإريك شميدت الرئيس التنفيذي السابق لجوجل، وفينود خوسلا الملياردير التقني. البيان الذي حمل عنوان «يجب أن نتحرك الآن» يحذر من أن الذكاء الاصطناعي قد يصبح أقوى بصورة جذرية خلال العشر سنوات المقبلة، وقد يحمل مخاطر كبيرة مثل نزوح جماعي للوظائف، إلى جانب فرص هائلة لارتفاع مستويات المعيشة، لكن ما يميز هذا البيان ليس فقط عدد الموقّعين، بل طبيعتهم، فمن بينهم اقتصاديون كانوا في الماضي ينظرون إلى تحذيرات الذكاء الاصطناعي بقدر كبير من الحذر، مثل دارون أسيموغلو، وسيمون جونسون، من معهد ماساتشوستس للتكنولوجيا، والحائزان على جائزة نوبل عام 2024، أما اليوم، فإنهما يعترفان بأن الذكاء الاصطناعي يسير بوتيرة أسرع وأعمق مما توقعوا، وقد يفوق تأثيره الثورة الصناعية من حيث الحجم، لكنه يحدث في إطار زمني أقصر بكثير. يتزامن هذا التحذير مع تحولات عالمية بالغة السرعة، فالذكاء الاصطناعي لم يعد يقتصر على المهام الروتينية، بل بدأ ينافس الوظائف المعرفية والإبداعية التي كانت تعتبر آمنة، والاقتصاديون الذين كانوا يرون في التكنولوجيا قوة خلاقة دائماً، أصبحوا اليوم أكثر قلقاً من سرعة التحول، ومن عدم استعداد المجتمعات والحكومات لمواجهة تداعياته، ويخطئ من يظن أن البيان التحذيري يدعو إلى وقف تطوير الذكاء الاصطناعي، بل يطالب بالعمل الجاد لفهم آثاره الاقتصادية، وبناء الحوافز والضمانات والمؤسسات اللازمة لتوجيه التكنولوجيا باتجاه تكاملي مع الإنسان وخدمة المجتمع، ولا يحل محله إطلاقاً. في عالمنا العربي والإسلامي، وفي ظل رؤي 2030 الطموحة التي تضع الذكاء الاصطناعي في قلب استراتيجيتها التنموية، فإن هذا البيان يحمل رسالة بالغة الأهمية بالنسبة لنا، لأننا بحاجة إلى الاستفادة من الفرص الهائلة التي يوفرها الذكاء الاصطناعي في رفع الإنتاجية وخلق وظائف جديدة، وفي الوقت ذاته يجب أن نعد أنفسنا جيداً لمواجهة تحدياته، خاصة في مجال الوظائف والتدريب والحماية الاجتماعية، فالذكاء الاصطناعي ليس مصيراً محتوماً، بل أداة بيدنا، والسؤال الذي يجب أن نطرحه على أنفسنا اليوم ليس «هل سيغير الذكاء الاصطناعي اقتصادنا؟»، بل «كيف نجعله يخدم أهدافنا الوطنية ويحافظ على كرامة الإنسان واستقرار مجتمعاتنا؟»، ولهذا يجب أن ننتهز الوقت للعمل الجاد والمبكر، لأن التاريخ لا يرحم من تأخروا عن مواكبة التحولات الكبرى.", "url": "https://www.alriyadh.com/%3Ehttp:/www.alriyadh.com/2199232", "urlToImage": "", "publishedAt": "2026-07-23 20:21:34", "source": {"name": "alriyadh"}}, {"title": "“واتساب” يتيح إنشاء حسابات مستقلة على أجهزة آيباد - صحيفة سويفت نيوز", "description": "“واتساب” يتيح إنشاء حسابات مستقلة على أجهزة آيباد صحيفة سويفت نيوز \"واتساب\" على آيباد يستغني أخيرًا عن الآيفون العربية WhatsApp iPad يمكنه الانضمام مباشرة دون iPhone VOI.ID WhatsApp يحصل على ترقية ضخمة لـ CarPlayفي السيارة إلىoneبإمكانه فعل أي شيء تقريباً تريده أن يفعله. Letem světem Applem بدلاً من iCloud.. ميتا تختبر تخزين محادثات واتساب على خوادمها الشرق للأخبار", "url": "https://news.google.com/rss/articles/CBMiTkFVX3lxTE5YRzF4LUljc2U3Y2JKZkcxWEp5SVBFRjhmUFp6ZzRybmt4ZTZNNXVET1pKX2d6TVhwdWNnNVVPMHN1cDJJRzVBZl94YWJwUQ?oc=5", "urlToImage": "", "publishedAt": "2026-07-23 18:57:55", "source": {"name": "google"}}, {"title": "فيديو سيلفي لتسجيل الدخول.. جوجل تطلق ميزة جديدة لتعزيز أمان الحسابات", "description": "أعلنت شركة جوجل، التابعة لشركة ألفابت، إطلاق ميزة جديدة تتيح للمستخدمين تسجيل الدخول إلى حساباتهم أو استعادتها باستخدام فيديو سيلفي، في خطوة تستهدف تعزيز أمان الحسابات وتسهيل الوصول إليها عند فقدان وسائل التحقق التقليدية مثل كلمات المرور أو الأجهزة الموثوقة. وتوفر الميزة خيارًا اختياريًا للمستخدمين، حيث يمكنهم تفعيلها ضمن إعدادات الأمان للاستفادة منها عند الحاجة، [...] تم نشر هذه المقالة فيديو سيلفي لتسجيل الدخول.. جوجل تطلق ميزة جديدة لتعزيز أمان الحسابات للمرة الأولي علي صحيفة الوئام .", "url": "https://www.alweeam.com.sa/1286859/2026/%D9%81%D9%8A%D8%AF%D9%8A%D9%88-%D8%B3%D9%8A%D9%84%D9%81%D9%8A-%D9%84%D8%AA%D8%B3%D8%AC%D9%8A%D9%84-%D8%A7%D9%84%D8%AF%D8%AE%D9%88%D9%84-%D8%AC%D9%88%D8%AC%D9%84-%D8%AA%D8%B7%D9%84%D9%82-%D9%85%D9%8A/", "urlToImage": "https://www.alweeam.com.sa/wp-content/uploads/2026/07/%D8%AC%D9%88%D9%88-1.jpg", "publishedAt": "2026-07-23 18:49:58", "source": {"name": "alweeam"}}], "totalArticles": 19}